topsis/101903144.py
topsis_ARYAN_101903144-1.0.0.dist-info/LICENSE
topsis_ARYAN_101903144-1.0.0.dist-info/METADATA
topsis_ARYAN_101903144-1.0.0.dist-info/WHEEL
topsis_ARYAN_101903144-1.0.0.dist-info/top_level.txt
topsis_ARYAN_101903144-1.0.0.dist-info/RECORD
