Metadata-Version: 2.1
Name: topsis-ARYAN-101903144
Version: 1.0.0
Summary: Multiple criteria decision making (MCDM) using TOPSIS
Author: Aryan Garg
Author-email: aryangarg111109@gmail.com
License: MIT
Platform: UNKNOWN
Classifier: License :: OSI Approved :: MIT License
Classifier: Programming Language :: Python :: 3.6
Classifier: Programming Language :: Python :: 3.7
Classifier: Programming Language :: Python :: 3.8
Classifier: Programming Language :: Python :: 3.9
License-File: LICENSE
